{
    "os": "Linux-5.4.0-150-generic-x86_64-with-glibc2.31",
    "python": "3.9.17",
    "heartbeatAt": "2023-09-04T23:26:08.480300",
    "startedAt": "2023-09-04T23:26:07.754173",
    "docker": null,
    "cuda": null,
    "args": [
        "lmnav/configs/habitat/train_imagenav_hm3d.yaml"
    ],
    "state": "running",
    "program": "/coc/testnvme/pputta7/projects/lm-nav/lmnav/bc_train.py",
    "codePath": "lmnav/bc_train.py",
    "git": {
        "remote": "https://github.com/pranav-putta/lm-nav.git",
        "commit": "22306bddbb32088acbcd10f9da5faa5f858a79e4"
    },
    "email": "pranav.putta22@gmail.com",
    "root": "/coc/testnvme/pputta7/projects/lm-nav",
    "host": "clippy",
    "username": "pputta7",
    "executable": "/coc/testnvme/pputta7/mambaforge/envs/lmnav/bin/python",
    "cpu_count": 64,
    "cpu_count_logical": 128,
    "cpu_freq": {
        "current": 2478.8322109375003,
        "min": 1500.0,
        "max": 2350.0
    },
    "cpu_freq_per_core": [
        {
            "current": 3182.104,
            "min": 1500.0,
            "max": 2350.0
        },
        {
            "current": 1991.876,
            "min": 1500.0,
            "max": 2350.0
        },
        {
            "current": 1609.719,
            "min": 1500.0,
            "max": 2350.0
        },
        {
            "current": 1612.07,
            "min": 1500.0,
            "max": 2350.0
        },
        {
            "current": 3186.406,
            "min": 1500.0,
            "max": 2350.0
        },
        {
            "current": 1613.183,
            "min": 1500.0,
            "max": 2350.0
        },
        {
            "current": 1610.093,
            "min": 1500.0,
            "max": 2350.0
        },
        {
            "current": 1610.926,
            "min": 1500.0,
            "max": 2350.0
        },
        {
            "current": 2522.087,
            "min": 1500.0,
            "max": 2350.0
        },
        {
            "current": 1611.27,
            "min": 1500.0,
            "max": 2350.0
        },
        {
            "current": 3224.743,
            "min": 1500.0,
            "max": 2350.0
        },
        {
            "current": 1608.73,
            "min": 1500.0,
            "max": 2350.0
        },
        {
            "current": 3179.134,
            "min": 1500.0,
            "max": 2350.0
        },
        {
            "current": 2989.511,
            "min": 1500.0,
            "max": 2350.0
        },
        {
            "current": 2379.346,
            "min": 1500.0,
            "max": 2350.0
        },
        {
            "current": 2374.917,
            "min": 1500.0,
            "max": 2350.0
        },
        {
            "current": 2292.222,
            "min": 1500.0,
            "max": 2350.0
        },
        {
            "current": 2355.329,
            "min": 1500.0,
            "max": 2350.0
        },
        {
            "current": 1720.274,
            "min": 1500.0,
            "max": 2350.0
        },
        {
            "current": 3222.483,
            "min": 1500.0,
            "max": 2350.0
        },
        {
            "current": 3212.27,
            "min": 1500.0,
            "max": 2350.0
        },
        {
            "current": 3223.867,
            "min": 1500.0,
            "max": 2350.0
        },
        {
            "current": 3216.507,
            "min": 1500.0,
            "max": 2350.0
        },
        {
            "current": 3231.413,
            "min": 1500.0,
            "max": 2350.0
        },
        {
            "current": 3224.908,
            "min": 1500.0,
            "max": 2350.0
        },
        {
            "current": 3224.389,
            "min": 1500.0,
            "max": 2350.0
        },
        {
            "current": 3234.583,
            "min": 1500.0,
            "max": 2350.0
        },
        {
            "current": 3217.832,
            "min": 1500.0,
            "max": 2350.0
        },
        {
            "current": 3198.312,
            "min": 1500.0,
            "max": 2350.0
        },
        {
            "current": 3228.742,
            "min": 1500.0,
            "max": 2350.0
        },
        {
            "current": 3198.201,
            "min": 1500.0,
            "max": 2350.0
        },
        {
            "current": 3223.745,
            "min": 1500.0,
            "max": 2350.0
        },
        {
            "current": 3307.249,
            "min": 1500.0,
            "max": 2350.0
        },
        {
            "current": 1637.317,
            "min": 1500.0,
            "max": 2350.0
        },
        {
            "current": 1648.013,
            "min": 1500.0,
            "max": 2350.0
        },
        {
            "current": 1561.44,
            "min": 1500.0,
            "max": 2350.0
        },
        {
            "current": 3244.395,
            "min": 1500.0,
            "max": 2350.0
        },
        {
            "current": 1647.221,
            "min": 1500.0,
            "max": 2350.0
        },
        {
            "current": 1575.711,
            "min": 1500.0,
            "max": 2350.0
        },
        {
            "current": 1654.964,
            "min": 1500.0,
            "max": 2350.0
        },
        {
            "current": 1798.539,
            "min": 1500.0,
            "max": 2350.0
        },
        {
            "current": 1797.386,
            "min": 1500.0,
            "max": 2350.0
        },
        {
            "current": 1798.165,
            "min": 1500.0,
            "max": 2350.0
        },
        {
            "current": 1799.308,
            "min": 1500.0,
            "max": 2350.0
        },
        {
            "current": 3298.888,
            "min": 1500.0,
            "max": 2350.0
        },
        {
            "current": 3222.413,
            "min": 1500.0,
            "max": 2350.0
        },
        {
            "current": 3312.879,
            "min": 1500.0,
            "max": 2350.0
        },
        {
            "current": 2598.345,
            "min": 1500.0,
            "max": 2350.0
        },
        {
            "current": 3244.944,
            "min": 1500.0,
            "max": 2350.0
        },
        {
            "current": 1654.377,
            "min": 1500.0,
            "max": 2350.0
        },
        {
            "current": 1653.368,
            "min": 1500.0,
            "max": 2350.0
        },
        {
            "current": 1653.365,
            "min": 1500.0,
            "max": 2350.0
        },
        {
            "current": 1798.139,
            "min": 1500.0,
            "max": 2350.0
        },
        {
            "current": 1799.986,
            "min": 1500.0,
            "max": 2350.0
        },
        {
            "current": 1715.698,
            "min": 1500.0,
            "max": 2350.0
        },
        {
            "current": 1796.808,
            "min": 1500.0,
            "max": 2350.0
        },
        {
            "current": 1798.703,
            "min": 1500.0,
            "max": 2350.0
        },
        {
            "current": 1978.768,
            "min": 1500.0,
            "max": 2350.0
        },
        {
            "current": 1799.399,
            "min": 1500.0,
            "max": 2350.0
        },
        {
            "current": 1799.75,
            "min": 1500.0,
            "max": 2350.0
        },
        {
            "current": 3300.352,
            "min": 1500.0,
            "max": 2350.0
        },
        {
            "current": 3295.319,
            "min": 1500.0,
            "max": 2350.0
        },
        {
            "current": 3229.481,
            "min": 1500.0,
            "max": 2350.0
        },
        {
            "current": 3302.487,
            "min": 1500.0,
            "max": 2350.0
        },
        {
            "current": 3223.408,
            "min": 1500.0,
            "max": 2350.0
        },
        {
            "current": 2324.218,
            "min": 1500.0,
            "max": 2350.0
        },
        {
            "current": 1608.273,
            "min": 1500.0,
            "max": 2350.0
        },
        {
            "current": 1598.471,
            "min": 1500.0,
            "max": 2350.0
        },
        {
            "current": 3202.516,
            "min": 1500.0,
            "max": 2350.0
        },
        {
            "current": 1593.509,
            "min": 1500.0,
            "max": 2350.0
        },
        {
            "current": 1597.078,
            "min": 1500.0,
            "max": 2350.0
        },
        {
            "current": 1599.839,
            "min": 1500.0,
            "max": 2350.0
        },
        {
            "current": 3206.846,
            "min": 1500.0,
            "max": 2350.0
        },
        {
            "current": 1596.592,
            "min": 1500.0,
            "max": 2350.0
        },
        {
            "current": 3190.967,
            "min": 1500.0,
            "max": 2350.0
        },
        {
            "current": 1598.452,
            "min": 1500.0,
            "max": 2350.0
        },
        {
            "current": 3201.966,
            "min": 1500.0,
            "max": 2350.0
        },
        {
            "current": 1597.724,
            "min": 1500.0,
            "max": 2350.0
        },
        {
            "current": 3190.278,
            "min": 1500.0,
            "max": 2350.0
        },
        {
            "current": 3195.486,
            "min": 1500.0,
            "max": 2350.0
        },
        {
            "current": 3184.374,
            "min": 1500.0,
            "max": 2350.0
        },
        {
            "current": 3195.924,
            "min": 1500.0,
            "max": 2350.0
        },
        {
            "current": 3205.901,
            "min": 1500.0,
            "max": 2350.0
        },
        {
            "current": 3192.21,
            "min": 1500.0,
            "max": 2350.0
        },
        {
            "current": 3193.174,
            "min": 1500.0,
            "max": 2350.0
        },
        {
            "current": 3194.046,
            "min": 1500.0,
            "max": 2350.0
        },
        {
            "current": 3192.898,
            "min": 1500.0,
            "max": 2350.0
        },
        {
            "current": 3202.154,
            "min": 1500.0,
            "max": 2350.0
        },
        {
            "current": 3194.188,
            "min": 1500.0,
            "max": 2350.0
        },
        {
            "current": 3194.187,
            "min": 1500.0,
            "max": 2350.0
        },
        {
            "current": 3194.749,
            "min": 1500.0,
            "max": 2350.0
        },
        {
            "current": 3197.857,
            "min": 1500.0,
            "max": 2350.0
        },
        {
            "current": 3191.03,
            "min": 1500.0,
            "max": 2350.0
        },
        {
            "current": 3193.327,
            "min": 1500.0,
            "max": 2350.0
        },
        {
            "current": 3200.664,
            "min": 1500.0,
            "max": 2350.0
        },
        {
            "current": 3191.403,
            "min": 1500.0,
            "max": 2350.0
        },
        {
            "current": 3281.919,
            "min": 1500.0,
            "max": 2350.0
        },
        {
            "current": 1649.313,
            "min": 1500.0,
            "max": 2350.0
        },
        {
            "current": 1648.895,
            "min": 1500.0,
            "max": 2350.0
        },
        {
            "current": 1647.693,
            "min": 1500.0,
            "max": 2350.0
        },
        {
            "current": 3299.903,
            "min": 1500.0,
            "max": 2350.0
        },
        {
            "current": 1650.344,
            "min": 1500.0,
            "max": 2350.0
        },
        {
            "current": 1649.557,
            "min": 1500.0,
            "max": 2350.0
        },
        {
            "current": 1570.91,
            "min": 1500.0,
            "max": 2350.0
        },
        {
            "current": 1658.709,
            "min": 1500.0,
            "max": 2350.0
        },
        {
            "current": 1783.466,
            "min": 1500.0,
            "max": 2350.0
        },
        {
            "current": 1792.958,
            "min": 1500.0,
            "max": 2350.0
        },
        {
            "current": 1800.101,
            "min": 1500.0,
            "max": 2350.0
        },
        {
            "current": 3270.784,
            "min": 1500.0,
            "max": 2350.0
        },
        {
            "current": 3269.288,
            "min": 1500.0,
            "max": 2350.0
        },
        {
            "current": 3270.593,
            "min": 1500.0,
            "max": 2350.0
        },
        {
            "current": 1646.878,
            "min": 1500.0,
            "max": 2350.0
        },
        {
            "current": 3308.575,
            "min": 1500.0,
            "max": 2350.0
        },
        {
            "current": 1648.445,
            "min": 1500.0,
            "max": 2350.0
        },
        {
            "current": 1647.336,
            "min": 1500.0,
            "max": 2350.0
        },
        {
            "current": 1648.055,
            "min": 1500.0,
            "max": 2350.0
        },
        {
            "current": 1798.026,
            "min": 1500.0,
            "max": 2350.0
        },
        {
            "current": 1795.537,
            "min": 1500.0,
            "max": 2350.0
        },
        {
            "current": 1746.42,
            "min": 1500.0,
            "max": 2350.0
        },
        {
            "current": 1662.972,
            "min": 1500.0,
            "max": 2350.0
        },
        {
            "current": 1577.457,
            "min": 1500.0,
            "max": 2350.0
        },
        {
            "current": 1709.253,
            "min": 1500.0,
            "max": 2350.0
        },
        {
            "current": 2449.068,
            "min": 1500.0,
            "max": 2350.0
        },
        {
            "current": 3014.57,
            "min": 1500.0,
            "max": 2350.0
        },
        {
            "current": 3257.876,
            "min": 1500.0,
            "max": 2350.0
        },
        {
            "current": 3259.416,
            "min": 1500.0,
            "max": 2350.0
        },
        {
            "current": 3322.122,
            "min": 1500.0,
            "max": 2350.0
        },
        {
            "current": 3258.27,
            "min": 1500.0,
            "max": 2350.0
        }
    ],
    "disk": {
        "total": 879.0163383483887,
        "used": 51.76591491699219
    },
    "gpu": "NVIDIA A40",
    "gpu_count": 8,
    "gpu_devices": [
        {
            "name": "NVIDIA A40",
            "memory_total": 48305799168
        },
        {
            "name": "NVIDIA A40",
            "memory_total": 48305799168
        },
        {
            "name": "NVIDIA A40",
            "memory_total": 48305799168
        },
        {
            "name": "NVIDIA A40",
            "memory_total": 48305799168
        },
        {
            "name": "NVIDIA A40",
            "memory_total": 48305799168
        },
        {
            "name": "NVIDIA A40",
            "memory_total": 48305799168
        },
        {
            "name": "NVIDIA A40",
            "memory_total": 48305799168
        },
        {
            "name": "NVIDIA A40",
            "memory_total": 48305799168
        }
    ],
    "memory": {
        "total": 503.7443733215332
    }
}
